{
  "data": [
    {
      "id": "MDEwOlJlcG9zaXRvcnkyOTE2NDYyMTM=",
      "name": "Heart-disease-Identification",
      "createdAt": "2020-08-31T07:31:06Z",
      "url": "https://github.com/sujikathir/Heart-disease-Identification",
      "description": "Given clinical parameters about a patient, can we predict whether or not they have heart disease?",
      "isFork": false,
      "languages": [
        {
          "name": "Jupyter Notebook",
          "iconifyClass": "logos-jupyter"
        }
      ]
    },
    {
      "id": "MDEwOlJlcG9zaXRvcnkzMjUzNTE2NTM=",
      "name": "Page-Rank-using-Parallel-processing",
      "createdAt": "2020-12-29T17:49:54Z",
      "url": "https://github.com/sujikathir/Page-Rank-using-Parallel-processing",
      "description": null,
      "isFork": false,
      "languages": [
        {
          "name": "Jupyter Notebook",
          "iconifyClass": "logos-jupyter"
        }
      ]
    },
    {
      "id": "MDEwOlJlcG9zaXRvcnkzMTQyMTc0MzE=",
      "name": "Sales-Forecasting",
      "createdAt": "2020-11-19T10:47:10Z",
      "url": "https://github.com/sujikathir/Sales-Forecasting",
      "description": "Predicting the Sales using Time-series forecasting for month-wise data.",
      "isFork": false,
      "languages": [
        {
          "name": "Jupyter Notebook",
          "iconifyClass": "logos-jupyter"
        }
      ]
    },
    {
      "id": "MDEwOlJlcG9zaXRvcnkzMjczMDcyNTM=",
      "name": "Sentiment-Analysis-using-Deep-Learning",
      "createdAt": "2021-01-06T12:38:07Z",
      "url": "https://github.com/sujikathir/Sentiment-Analysis-using-Deep-Learning",
      "description": null,
      "isFork": false,
      "languages": [
        {
          "name": "Jupyter Notebook",
          "iconifyClass": "logos-jupyter"
        }
      ]
    },
    {
      "id": "MDEwOlJlcG9zaXRvcnkzMjcwNjMwMDQ=",
      "name": "Time-Series-using-LSTM",
      "createdAt": "2021-01-05T16:57:06Z",
      "url": "https://github.com/sujikathir/Time-Series-using-LSTM",
      "description": "Forecasting using Time Series",
      "isFork": false,
      "languages": [
        {
          "name": "Jupyter Notebook",
          "iconifyClass": "logos-jupyter"
        }
      ]
    }
  ]
}
